Workbook

Sheet Summary
A1: GravityX - Detailed Use of Funds (€800,000)
A3: Use of proceeds objective | B3: Scale GravityX from pilot-stage traction and early revenue into repeatable industrial production infrastructure: expand the core team, harden the next-generation platform, increase in-house capacity, and convert pilots into larger aerospace and defense manufacturing programs.
A5: Funding Allocation Summary
A6: Category | B6: Amount (€) | C6: % of Round | D6: Core Use | E6: Rationale | F6: Phase Focus | G6: View?
A7: Hiring | B7: =SUMIFS('Detailed Budget'!$F:$F,'Detailed Budget'!$A:$A,A7) -> 294000 | C7: =B7/$B$13 -> 0.38888889 | D7: Engineering, BD, sales, selective contractor support | E7: People are the primary scaling constraint in a deep-tech hardware company | F7: Months 1-12 | G7: Execution capacity
A8: Engineering & R&D | B8: =SUMIFS('Detailed Budget'!$F:$F,'Detailed Budget'!$A:$A,A8) -> 256000 | C8: =B8/$B$13 -> 0.33862434 | D8: Hardware hardening, automation, materials, testing, documentation | E8: Platform reliability and process control are the moat | F8: Months 1-12 | G8: Technology moat
A9: Production Capacity Expansion | B9: =SUMIFS('Detailed Budget'!$F:$F,'Detailed Budget'!$A:$A,A9) -> 105000 | C9: =B9/$B$13 -> 0.13888889 | D9: New internal cells, inventory, assembly tooling, QA equipment | E9: Turns capital directly into manufacturing throughput and revenue capacity | F9: Months 3-12 | G9: Commercial scaling
A10: Go-to-Market | B10: =SUMIFS('Detailed Budget'!$F:$F,'Detailed Budget'!$A:$A,A10) -> 26000 | C10: =B10/$B$13 -> 0.034391534 | D10: Travel, pilots, demos, defense/space events, sales systems | E10: Industrial sales require technical trust-building and on-site engagement | F10: Months 1-12 | G10: Pipeline conversion
A11: Operations & G&A | B11: =SUMIFS('Detailed Budget'!$F:$F,'Detailed Budget'!$A:$A,A11) -> 75000 | C11: =B11/$B$13 -> 0.099206349 | D11: Rent, utilities, legal, accounting, software, insurance, logistics | E11: Lean operating base with low rent and practical overhead | F11: Months 1-12 | G11: Execution support
A13: Total | B13: =SUM(B7:B11) -> 756000 | C13: =SUM(C7:C11) -> 1
A15: Key Budget Messages
B16: 1. Talent and engineering represent the majority of spend, matching GravityX's current stage as a hardware + automation company still hardening the platform.
B17: 2. Rent is intentionally capped at €10k for the full year. The company remains operationally lean and puts capital into engineering and production capacity instead of fixed overhead.
B18: 3. Production capacity expansion is split out separately from R&D to show that part of the round directly converts into higher throughput and near-term revenue capability.
B19: 4. The model is built for a 12-month execution window, with most spend linked to milestones that improve either reliability, output, or commercial conversion.

Sheet Detailed Budget
A1: Detailed Budget by Line Item
A3: Category | B3: Process (managment, Engineering, Rnd, Ops, Sales and marketing, Support) | C3: Cost Category (Salary, goods, services) | D3: Line Item | E3: Description | F3: Amount (€) | G3: % of Round | H3: Timing | I3: Type | J3: Priority | K3: Comment
A4: Hiring | D4: Founder's salaries (Viktoras, Martynas) | E4: Owns next-gen machine architecture, DFM/DFA, reliability | F4: 88000 | G4: =F4/$F$38 -> 0.11167513 | H4: Months 1-12 | I4: Input | J4: High | K4: FTE, Core
A5: Engineering & R&D | D5: Software Engineer (Simonas) | E5: Automation, monitoring, API, fleet-control foundation | F5: 28000 | G5: =F5/$F$38 -> 0.035532995 | H5: Months 6-12 | I5: Input | J5: Medium | K5: Services, Leverage across all future cells
A6: Hiring | D6: Manufacturing Engineer (New) | E6: Print process hardening, materials, production readiness | F6: 30000 | G6: =F6/$F$38 -> 0.038071066 | H6: Months 1-12 | I6: Input | J6: High | K6: FTE, Directly tied to repeatability
A7: Hiring | D7: Business Development (Rokas) | E7: Defense / aerospace pipeline conversion, partnerships, sales | F7: 44000 | G7: =F7/$F$38 -> 0.055837563 | H7: Months 1-12 | I7: Input | J7: High | K7: FTE, Revenue-facing role
A8: Hiring | D8: Logistics Co-ordinator (Tomas) | E8: Logistics | F8: 24000 | G8: =F8/$F$38 -> 0.030456853 | H8: Months 1-12 | I8: Input | J8: High | K8: FTE, Support
A9: Hiring | D9: Mechanical Engineer (Alexey) | E9: Engineering of structural and motion systems | F9: 36000 | G9: =F9/$F$38 -> 0.045685279 | H9: Months 1-12 | I9: Input | J9: Medium | K9: FTE, Mechanics/Robotics
A10: Hiring | D10: Engineer Generalist (Vilius) | E10: General Engineering (Full-Stack, SW-HW) | F10: 44000 | G10: =F10/$F$38 -> 0.055837563 | H10: Months 1-12 | I10: Input | J10: High | K10: FTE, Everything in general area of Engineering.
A11: Hiring | D11: Telemetry Data Analyst (Dovydas) interns, retention buffer | E11: Short-term experts, student help, retention support | F11: 56000 | G11: =F11/$F$38 -> 0.07106599 | H11: Months 1-12 | I11: Input | J11: Medium | K11: PTE, Flexibility for hard-to-plan needs
A12: Engineering & R&D | D12: Next-gen cell prototype iterations | E12: Frames, enclosure revisions, motion upgrades, redesign cycles | F12: 52000 | G12: =F12/$F$38 -> 0.065989848 | H12: Months 1-6 | I12: Input | J12: High | K12: Core product development
A13: Engineering & R&D | D13: Thermal / chamber / hot-end development | E13: Controlled thermal environment and high-temp subsystem work | F13: 30000 | G13: =F13/$F$38 -> 0.038071066 | H13: Months 1-6 | I13: Input | J13: High | K13: Critical for super-polymers
A14: Engineering & R&D | D14: Toolchanger & automation subsystem | E14: Multi-tool reliability, changeover mechanisms, automation hooks | F14: 24000 | G14: =F14/$F$38 -> 0.030456853 | H14: Months 2-8 | I14: Input | J14: High | K14: Supports manufactorum path
A15: Engineering & R&D | D15: Sensors / electronics / control stack | E15: Instrumentation, boards, harnesses, sensors, embedded control | F15: 18000 | G15: =F15/$F$38 -> 0.02284264 | H15: Months 1-8 | I15: Input | J15: Medium | K15: Enables monitoring and traceability
... A25: Go-to-Market | D25: Defense / aerospace trade events | E25: Targeted conferences, passes, stands, materials | F25: 18000 | G25: =F25/$F$38 -> 0.02284264 | H25: Months 4-12 | I25: Input | J25: Medium | K25: Focused industry access
A26: Go-to-Market | C26: Services | D26: Customer travel & site visits | E26: Technical reviews, customer meetings, pipeline conversion | F26: 10000 | G26: =F26/$F$38 -> 0.012690355 | H26: Months 1-12 | I26: Input | J26: High | K26: Industrial sales need presence
A27: Go-to-Market | C27: Services | D27: Pilot support / demo parts | E27: Sample builds, pilot setup, technical onboarding | F27: 16000 | G27: =F27/$F$38 -> 0.020304569 | H27: Months 1-12 | I27: Input | J27: High | K27: Converts technical interest
A28: Go-to-Market | C28: Services | D28: Website, deck, content, PR | E28: Messaging refresh, media, visual assets, investor/customer collateral. | F28: 8000 | G28: =F28/$F$38 -> 0.010152284 | H28: Months 1-12 | I28: Input | J28: Low | K28: Lean external visibility
A29: Go-to-Market | D29: CRM / sales systems | E29: Pipeline tooling, subscriptions, proposal stack | F29: 6000 | G29: =F29/$F$38 -> 0.0076142132 | H29: Months 1-12 | I29: Input | J29: Low | K29: Commercial hygiene
A30: Operations & G&A | D30: Workshop / lab rent | E30: Dedicated development and light production space | F30: 10000 | G30: =F30/$F$38 -> 0.012690355 | H30: Months 1-12 | I30: Input | J30: High | K30: Capped low on purpose
A31: Operations & G&A | D31: Utilities & internet | E31: Power, heating, connectivity, network | F31: 8000 | G31: =F31/$F$38 -> 0.010152284 | H31: Months 1-12 | I31: Input | J31: High | K31: Continuous testing support
A32: Operations & G&A | D32: Insurance | E32: Equipment, liability, facility coverage | F32: 7000 | G32: =F32/$F$38 -> 0.0088832487 | H32: Months 1-12 | I32: Input | J32: Medium | K32: Industrial prudence
A33: Operations & G&A | D33: Legal & accounting | E33: UAB setup, contracts, bookkeeping, governance, diligence | F33: 20000 | G33: =F33/$F$38 -> 0.025380711 | H33: Months 1-12 | I33: Input | J33: High | K33: Investor + customer readiness
A34: Operations & G&A | D34: Cloud & software subscriptions | E34: CAD, collaboration, storage, monitoring, email, ops tools | F34: 8000 | G34: =F34/$F$38 -> 0.010152284 | H34: Months 1-12 | I34: Input | J34: Medium | K34: Lean software overhead
A35: Operations & G&A | D35: Shipping & logistics | E35: Inbound components, outbound parts, packaging, freight | F35: 12000 | G35: =F35/$F$38 -> 0.015228426 | H35: Months 1-12 | I35: Input | J35: Medium | K35: Hardware reality
A36: Operations & G&A | D36: Computers / admin equipment | E36: Practical office and engineering peripherals | F36: 5000 | G36: =F36/$F$38 -> 0.0063451777 | H36: Months 1-6 | I36: Input | J36: Low | K36: One-off setup items
A37: Operations & G&A | D37: Security / backups / IT | E37: Backups, secure comms, access control, cyber basics | F37: 5000 | G37: =F37/$F$38 -> 0.0063451777 | H37: Months 1-12 | I37: Input | J37: Low | K37: Especially relevant for defense work
E38: Total | F38: =SUM(F4:F37) -> 788000
A40: Category Check
A41: Category | D41: Actual (€) | E41: Expected (€) | F41: Variance (€) | G41: % of Round
A42: Hiring | D42: =SUMIF($A$4:$A$37,A42,$F$4:$F$37) -> 322000 | E42: 350000 | F42: =D42-E42 -> -28000 | G42: =D42/$F$38 -> 0.40862944
A43: Engineering & R&D | D43: =SUMIF($A$4:$A$37,A43,$F$4:$F$37) -> 228000 | E43: 200000 | F43: =D43-E43 -> 28000 | G43: =D43/$F$38 -> 0.2893401
A44: Production Capacity Expansion | D44: =SUMIF($A$4:$A$37,A44,$F$4:$F$37) -> 105000 | E44: 105000 | F44: =D44-E44 -> 0 | G44: =D44/$F$38 -> 0.13324873
A45: Go-to-Market | D45: =SUMIF($A$4:$A$37,A45,$F$4:$F$37) -> 48000 | E45: 70000 | F45: =D45-E45 -> -22000 | G45: =D45/$F$38 -> 0.060913706
A46: Operations & G&A | D46: =SUMIF($A$4:$A$37,A46,$F$4:$F$37) -> 75000 | E46: 75000 | F46: =D46-E46 -> 0 | G46: =D46/$F$38 -> 0.095177665

Sheet 12M Cash Plan
A1: 12-Month Cash Deployment Plan
A3: Category / Line Item | B3: M1 | C3: M2 | D3: M3 | E3: M4 | F3: M5 | G3: M6 | H3: M7 | I3: M8 | J3: M9 | K3: M10 | L3: M11 | M3: M12 | N3: Total (€) | O3: % of Round | P3: Comment
A4: Hiring | B4: 18000 | C4: 22000 | D4: 26000 | E4: 30000 | F4: 30000 | G4: 30000 | H4: 30000 | I4: 30000 | J4: 30000 | K4: 30000 | L4: 30000 | M4: 24000 | N4: =SUM(B4:M4) -> 330000 | O4: =N4/$N$10 -> 0.42307692 | P4: Ramp-up then steady team burn
A5: Engineering & R&D | Prototype hardening, testing, materials, tooling | B5: 20000 | C5: 24000 | D5: 26000 | E5: 22000 | F5: 18000 | G5: 18000 | H5: 15000 | I5: 14000 | J5: 13000 | K5: 12000 | L5: 9000 | M5: 9000 | N5: =SUM(B5:M5) -> 200000 | O5: =N5/$N$10 -> 0.25641026 | P5: Front-loaded technical development
A6: Production Capacity Expansion | Cells, inventory, benches, QA equipment | B6: 0 | C6: 5000 | D6: 12000 | E6: 15000 | F6: 15000 | G6: 13000 | H6: 10000 | I6: 10000 | J6: 10000 | K6: 5000 | L6: 5000 | M6: 5000 | N6: =SUM(B6:M6) -> 105000 | O6: =N6/$N$10 -> 0.13461538 | P6: Capacity comes after early hardening
A7: Go-to-Market | Travel, pilots, events, sales systems | B7: 3000 | C7: 4000 | D7: 5000 | E7: 6000 | F7: 7000 | G7: 7000 | H7: 7000 | I7: 7000 | J7: 7000 | K7: 6000 | L7: 6000 | M7: 5000 | N7: =SUM(B7:M7) -> 70000 | O7: =N7/$N$10 -> 0.08974359 | P7: Commercial expansion alongside capacity
A8: Operations & G&A | Rent, utilities, legal, software, insurance, logistics | B8: 5000 | C8: 6000 | D8: 7000 | E8: 6000 | F8: 6000 | G8: 6000 | H8: 7000 | I8: 7000 | J8: 6000 | K8: 7000 | L8: 6000 | M8: 6000 | N8: =SUM(B8:M8) -> 75000 | O8: =N8/$N$10 -> 0.096153846 | P8: Lean fixed base + legal / logistics cadence
A10: Total by month | B10: =SUM(B4:B8) -> 46000 | C10: =SUM(C4:C8) -> 61000 | D10: =SUM(D4:D8) -> 76000 | E10: =SUM(E4:E8) -> 79000 | F10: =SUM(F4:F8) -> 76000 | G10: =SUM(G4:G8) -> 74000 | H10: =SUM(H4:H8) -> 69000 | I10: =SUM(I4:I8) -> 68000 | ... O10: =SUM(O4:O8) -> 1

Sheet Hiring Plan
A1: Hiring and Retention Plan
A3: Role | B3: Function | C3: Planned Start | D3: 12M Cost (€) | E3: Why this role matters | F3: Revenue / Product Impact | G3: Priority | H3: Current Need | I3: Notes
A4: Founder's salaries | B4: Core | C4: Month 1 | D4: 88000 | E4: Own platform architecture and production robustness | F4: Founding Team | G4: High | H4: Immediate | I4: Critical deep-tech hire
A5: Software Engineer | B5: Automation / software | C5: Month 6 | D5: 28000 | E5: Build monitoring, API, automation, data systems | F5: Multiplies future manufactorum value | G5: Medium | H5: Ongoing | I5: Leverage role
A6: Manufacturing Engineer | B6: Production process | C6: Month 1 | D6: 30000 | E6: Own material/process repeatability and readiness | F6: Directly improves throughput and scrap rate | G6: High | H6: Immediate | I6: Core production role
A7: Business Development | B7: Commercial | C7: Month 1 | D7: 44000 | E7: Convert pilots into contracts and open pipeline | F7: Direct revenue role | G7: High | H7: Immediate | I7: Defense / aerospace focus
A8: Logistics Co-ordinator | B8: Logistics | C8: Month 1 | D8: 24000 | E8: Coordinates and plans logistics, keeps inventory track | F8: Eleviates logistical and packaging problems | G8: High | H8: Immediate | I8: Core planing/execution role
A9: Mechanical Engineer | B9: R&D | C9: Month 1 | D9: 36000 | E9: Engineering of structural and motion systems | F9: R&D | G9: High | H9: Immediate | I9: Tech Hire
A10: Engineer Generalist | B10: R&D | C10: Month 1 | D10: 44000 | E10: General engineering help: design, assembly, soldering, manufacturing | F10: Full-stack day-to-day engineering operations | G10: High | H10: Immediate | I10: Core day to day role
A11: Specialists / interns / contractors | B11: Flexible support | C11: Rolling | D11: 56000 | E11: Add targeted expertise without overhiring too early | F11: Keeps core team focused | G11: Medium | H11: Ongoing | I11: Retention + flexibility bucket
C12: Total Talent Budget | D12: =SUM(D4:D11) -> 350000
